main.py
musicview/__init__.py
musicview/__version__.py
musicview/cli.py
musicview/db.py
musicview/misc.py
musicview/player.py
musicview/song.py
musicview-0.3.3.dist-info/DESCRIPTION.rst
musicview-0.3.3.dist-info/LICENSE.txt
musicview-0.3.3.dist-info/METADATA
musicview-0.3.3.dist-info/RECORD
musicview-0.3.3.dist-info/WHEEL
musicview-0.3.3.dist-info/entry_points.txt
musicview-0.3.3.dist-info/metadata.json
musicview-0.3.3.dist-info/top_level.txt
