Metadata-Version: 2.0
Name: musicview
Version: 0.3.3
Summary: (re)discover your music library.
Home-page: https://github.com/MaT1g3R/musicview
Author: Peijun Ma
Author-email: peijun.ma@protonmail.com
License: GPLv3.0+
Platform: UNKNOWN
Classifier: Development Status :: 3 - Alpha
Classifier: Environment :: Console
Classifier: Environment :: Console :: Curses
Classifier: Intended Audience :: End Users/Desktop
Classifier: Natural Language :: English
Classifier: License :: OSI Approved :: GNU General Public License v3 or later (GPLv3+)
Classifier: Programming Language :: Python
Classifier: Programming Language :: Python :: 3 :: Only
Classifier: Programming Language :: Python :: 3.6
Classifier: Programming Language :: Python :: 3.7
Classifier: Programming Language :: Python :: Implementation :: CPython
Classifier: Topic :: Multimedia :: Sound/Audio
Classifier: Topic :: Multimedia :: Sound/Audio :: Players
Classifier: Topic :: Multimedia :: Sound/Audio :: Players :: MP3
Requires-Python: >=3.6
Requires-Dist: click (>=6.7)
Requires-Dist: mutagen (>=1.40.0)
Requires-Dist: toml (>=0.9.4)
